chroma_gui/__init__.py
chroma_gui/__main__.py
chroma_gui/constants.py
chroma_gui/main.py
chroma_gui/chromaticity/__init__.py
chroma_gui/chromaticity/chroma_fct.py
chroma_gui/cleaning/__init__.py
chroma_gui/cleaning/clean.py
chroma_gui/cleaning/constants.py
chroma_gui/cleaning/plateau.py
chroma_gui/corrections/__init__.py
chroma_gui/corrections/response_matrix.py
chroma_gui/plotting/__init__.py
chroma_gui/plotting/functions.py
chroma_gui/plotting/widget.py
chroma_gui/resources/chroma_gui.mplstyle
chroma_gui/resources/chromaticity_coefficients.json
chroma_gui/resources/response_matrices.json
chroma_gui/resources/corrections/R2022a_A11mC11mA10mL10m/normal_decapole/complete_f1004_x_B1.csv
chroma_gui/resources/corrections/R2022a_A11mC11mA10mL10m/normal_decapole/complete_f1004_x_B2.csv
chroma_gui/resources/corrections/R2022a_A11mC11mA10mL10m/normal_decapole/ptc_normal_A12B1.tfs
chroma_gui/resources/corrections/R2022a_A11mC11mA10mL10m/normal_decapole/ptc_normal_A12B2.tfs
chroma_gui/resources/corrections/R2022a_A11mC11mA10mL10m/normal_decapole/ptc_normal_A23B1.tfs
chroma_gui/resources/corrections/R2022a_A11mC11mA10mL10m/normal_decapole/ptc_normal_A23B2.tfs
chroma_gui/resources/corrections/R2022a_A11mC11mA10mL10m/normal_decapole/ptc_normal_A34B1.tfs
chroma_gui/resources/corrections/R2022a_A11mC11mA10mL10m/normal_decapole/ptc_normal_A34B2.tfs
chroma_gui/resources/corrections/R2022a_A11mC11mA10mL10m/normal_decapole/ptc_normal_A45B1.tfs
chroma_gui/resources/corrections/R2022a_A11mC11mA10mL10m/normal_decapole/ptc_normal_A45B2.tfs
chroma_gui/resources/corrections/R2022a_A11mC11mA10mL10m/normal_decapole/ptc_normal_A56B1.tfs
chroma_gui/resources/corrections/R2022a_A11mC11mA10mL10m/normal_decapole/ptc_normal_A56B2.tfs
chroma_gui/resources/corrections/R2022a_A11mC11mA10mL10m/normal_decapole/ptc_normal_A67B1.tfs
chroma_gui/resources/corrections/R2022a_A11mC11mA10mL10m/normal_decapole/ptc_normal_A67B2.tfs
chroma_gui-0.0.26.dist-info/METADATA
chroma_gui-0.0.26.dist-info/WHEEL
chroma_gui-0.0.26.dist-info/RECORD
