Metadata-Version: 2.4
Name: chroma-gui
Version: 0.0.26
Summary: QT Graphical User Interface wrapper of the ``omc3`` package
Project-URL: homepage, https://github.com/pylhc/chroma_gui
Project-URL: repository, https://github.com/pylhc/chroma_gui
Project-URL: documentation, https://pylhc.github.io/chroma_gui/
Project-URL: changelog, https://github.com/pylhc/chroma_gui/blob/master/CHANGELOG.md
Author-email: OMC Team <pylhc@github.com>
License-Expression: MIT
Classifier: Intended Audience :: Science/Research
Classifier: License :: OSI Approved :: MIT License
Classifier: Natural Language :: English
Classifier: Operating System :: OS Independent
Classifier: Programming Language :: Python :: 3 :: Only
Classifier: Programming Language :: Python :: 3.10
Classifier: Programming Language :: Python :: 3.11
Classifier: Programming Language :: Python :: 3.12
Classifier: Programming Language :: Python :: 3.13
Classifier: Programming Language :: Python :: Implementation :: CPython
Classifier: Topic :: Scientific/Engineering
Classifier: Topic :: Scientific/Engineering :: Physics
Classifier: Topic :: Scientific/Engineering :: Visualization
Classifier: Topic :: Software Development :: Libraries :: Python Modules
Classifier: Typing :: Typed
Requires-Python: >=3.10
Requires-Dist: matplotlib
Requires-Dist: nafflib
Requires-Dist: numpy
Requires-Dist: pandas
Requires-Dist: pyperclip
Requires-Dist: pyqt5>=5.14
Requires-Dist: qtawesome
Requires-Dist: scipy
Requires-Dist: tables
Requires-Dist: tabulate
Requires-Dist: tfs-pandas
Provides-Extra: all
Requires-Dist: pytest>=7.0; extra == 'all'
Requires-Dist: pytimber; extra == 'all'
Requires-Dist: sphinx-rtd-theme>=2.0; extra == 'all'
Requires-Dist: sphinx>=7.0; extra == 'all'
Provides-Extra: cern
Requires-Dist: pytimber; extra == 'cern'
Provides-Extra: doc
Requires-Dist: sphinx-rtd-theme>=2.0; extra == 'doc'
Requires-Dist: sphinx>=7.0; extra == 'doc'
Provides-Extra: test
Requires-Dist: pytest>=7.0; extra == 'test'
